smplpytorch/__init__.py
smplpytorch/demo.py
smplpytorch/display_utils.py
smplpytorch/native/__init__.py
smplpytorch/native/webuser/__init__.py
smplpytorch/native/webuser/posemapper.py
smplpytorch/native/webuser/serialization.py
smplpytorch/pytorch/__init__.py
smplpytorch/pytorch/rodrigues_layer.py
smplpytorch/pytorch/smpl_layer.py
smplpytorch/pytorch/tensutils.py
smplpytorch-0.0.8.dist-info/LICENSE
smplpytorch-0.0.8.dist-info/METADATA
smplpytorch-0.0.8.dist-info/WHEEL
smplpytorch-0.0.8.dist-info/top_level.txt
smplpytorch-0.0.8.dist-info/RECORD
