Metadata-Version: 2.1
Name: smplpytorch
Version: 0.0.8
Summary: SMPL human body layer for PyTorch is a differentiable PyTorch layer
Home-page: https://github.com/gulvarol/smplpytorch
Author: Gul Varol
Author-email: gulvarols@gmail.com
License: UNKNOWN
Platform: UNKNOWN
Classifier: Programming Language :: Python :: 3
Classifier: License :: OSI Approved :: GNU General Public License v3 (GPLv3)
Classifier: Operating System :: OS Independent
Requires-Python: >=3.5.0
Requires-Dist: opencv-python
Requires-Dist: matplotlib
Requires-Dist: numpy
